hamutils/__init__.py
hamutils/version.py
hamutils/adif/__init__.py
hamutils/adif/adi.py
hamutils/adif/adx.py
hamutils/adif/common.py
hamutils/cabrillo/__init__.py
hamutils/cabrillo/cabrillo.py
hamutils/qrz/__init__.py
hamutils/qrz/__main__.py
hamutils/space_weather/__init__.py
hamutils/space_weather/__main__.py
hamutils/space_weather/geomagnetic_data.py
hamutils/space_weather/predictions.py
hamutils/space_weather/solar_data.py
hamutils-0.2.1.dist-info/LICENSE
hamutils-0.2.1.dist-info/METADATA
hamutils-0.2.1.dist-info/WHEEL
hamutils-0.2.1.dist-info/top_level.txt
hamutils-0.2.1.dist-info/RECORD
