Metadata-Version: 2.1
Name: hamutils
Version: 0.2.1
Summary: Amateur radio utils library
Home-page: https://github.com/sq8kfh/hamutils
Author: SQ8KFH
Author-email: sq8kfh@gmail.com
License: MIT
Download-URL: https://github.com/sq8kfh/hamutils/tarball/v0.2.1
Keywords: ham qrz space weather adif adi adx cabrillo
Platform: UNKNOWN
Classifier: Development Status :: 3 - Alpha
Classifier: Intended Audience :: Developers
Classifier: Topic :: Communications :: Ham Radio
Classifier: Topic :: Software Development :: Libraries :: Python Modules
Classifier: License :: OSI Approved :: MIT License
Classifier: Programming Language :: Python :: 3 :: Only
Classifier: Programming Language :: Python :: 3.4
Requires-Python: >=3.4
License-File: LICENSE
Requires-Dist: unidecode
